jcon/__init__.py
jcon/cli.py
jcon/core.py
jcon/layout.py
jcon-0.5.8.dist-info/licenses/LICENSE
jcon-0.5.8.dist-info/METADATA
jcon-0.5.8.dist-info/WHEEL
jcon-0.5.8.dist-info/top_level.txt
jcon-0.5.8.dist-info/RECORD
