Metadata-Version: 2.4
Name: jcon
Version: 0.5.8
Summary: Move Windows desktop icons programmatically in Python
Author: Jett S
Author-email: fallinganvil8@gmail.com
Classifier: Programming Language :: Python :: 3
Classifier: Operating System :: Microsoft :: Windows
Classifier: License :: OSI Approved :: MIT License
Requires-Python: >=3.6
License-File: LICENSE
Dynamic: author
Dynamic: author-email
Dynamic: classifier
Dynamic: description
Dynamic: description-content-type
Dynamic: license-file
Dynamic: requires-python
Dynamic: summary
